PyGCPM/GCPM.py
PyGCPM/PlotEqSlice.py
PyGCPM/PlotMLTSlice.py
PyGCPM/PlotPlanet.py
PyGCPM/_CFunctions.py
PyGCPM/__init__.py
PyGCPM/__data/libgcpm/gcpm.py
PyGCPM/__data/libgcpm/libgcpm.c
PyGCPM/__data/libgcpm/libgcpm.h
PyGCPM/__data/libgcpm/libgcpm.o
PyGCPM/__data/libgcpm/libgcpm.so
PyGCPM/__data/libgcpm/makefile
PyGCPM/__data/libgcpm/__pycache__/gcpm.cpython-36.pyc
PyGCPM/__data/libgcpm/gcpm/bulge.for
PyGCPM/__data/libgcpm/gcpm/bulge.o
PyGCPM/__data/libgcpm/gcpm/equatorial_view.pro
PyGCPM/__data/libgcpm/gcpm/fieldaligned_view.pro
PyGCPM/__data/libgcpm/gcpm/gcpm_v24.for
PyGCPM/__data/libgcpm/gcpm/gcpm_v24.o
PyGCPM/__data/libgcpm/gcpm/gcpm_v24_equatorial.jpg
PyGCPM/__data/libgcpm/gcpm/gcpm_v24_fieldaligned.jpg
PyGCPM/__data/libgcpm/gcpm/gcpm_v24_meridian_00h_12h_kp1p0.bin
PyGCPM/__data/libgcpm/gcpm/gcpm_v24_meridian_00h_12h_kp1p0.jpg
PyGCPM/__data/libgcpm/gcpm/gcpm_v24_meridian_01h_13h_kp1p0.bin
PyGCPM/__data/libgcpm/gcpm/gcpm_v24_meridian_01h_13h_kp1p0.jpg
PyGCPM/__data/libgcpm/gcpm/gcpm_v24_meridian_02h_14h_kp1p0.bin
PyGCPM/__data/libgcpm/gcpm/gcpm_v24_meridian_02h_14h_kp1p0.jpg
PyGCPM/__data/libgcpm/gcpm/gcpm_v24_meridian_03h_15h_kp1p0.bin
PyGCPM/__data/libgcpm/gcpm/gcpm_v24_meridian_03h_15h_kp1p0.jpg
PyGCPM/__data/libgcpm/gcpm/gcpm_v24_meridian_04h_16h_kp1p0.bin
PyGCPM/__data/libgcpm/gcpm/gcpm_v24_meridian_04h_16h_kp1p0.jpg
PyGCPM/__data/libgcpm/gcpm/gcpm_v24_meridian_05h_17h_kp1p0.bin
PyGCPM/__data/libgcpm/gcpm/gcpm_v24_meridian_05h_17h_kp1p0.jpg
PyGCPM/__data/libgcpm/gcpm/gcpm_v24_meridian_06h_18h_kp1p0.bin
PyGCPM/__data/libgcpm/gcpm/gcpm_v24_meridian_06h_18h_kp1p0.jpg
PyGCPM/__data/libgcpm/gcpm/gcpm_v24_meridian_07h_19h_kp1p0.bin
PyGCPM/__data/libgcpm/gcpm/gcpm_v24_meridian_07h_19h_kp1p0.jpg
PyGCPM/__data/libgcpm/gcpm/gcpm_v24_meridian_08h_20h_kp1p0.bin
PyGCPM/__data/libgcpm/gcpm/gcpm_v24_meridian_08h_20h_kp1p0.jpg
PyGCPM/__data/libgcpm/gcpm/gcpm_v24_meridian_09h_21h_kp1p0.bin
PyGCPM/__data/libgcpm/gcpm/gcpm_v24_meridian_09h_21h_kp1p0.jpg
PyGCPM-0.0.2.dist-info/LICENSE
PyGCPM-0.0.2.dist-info/METADATA
PyGCPM-0.0.2.dist-info/WHEEL
PyGCPM-0.0.2.dist-info/top_level.txt
PyGCPM-0.0.2.dist-info/RECORD
