Metadata-Version: 2.1
Name: PyGCPM
Version: 0.0.2
Summary: Python wrapper for the Global Core Plasma Model
Home-page: https://github.com/mattkjames7/PyGCPM
Author: Matthew Knight James
Author-email: mattkjames7@gmail.com
License: UNKNOWN
Platform: UNKNOWN
Classifier: Programming Language :: Python :: 3
Classifier: License :: OSI Approved :: GNU General Public License (GPL)
Classifier: Operating System :: POSIX
License-File: LICENSE
Requires-Dist: numpy
Requires-Dist: DateTimeTools (>=0.0.6)
Requires-Dist: matplotlib
